hews/__constants__.py
hews/__init__.py
hews/console.py
hews/core.py
hews/http_service.py
hews/libraries/__init__.py
hews/libraries/multiple_configs/__init__.py
hews/libraries/multiple_configs/main.py
hews/libraries/multiple_configs/single_configs.py
hews/libraries/multiple_configs/single_configs_by_empty.py
hews/libraries/multiple_configs/single_configs_by_file.py
hews/libraries/multiple_translations/__init__.py
hews/libraries/multiple_translations/main.py
hews/libraries/multiple_translations/single_translations.py
hews/libraries/terminal_command/__init__.py
hews/libraries/terminal_command/main.py
hews/system/__init__.py
hews/system/core.py
hews/system/client/__init__.py
hews/system/client/core.py
hews/system/projects/__init__.py
hews/system/projects/core.py
hews/system/projects/project/__init__.py
hews/system/projects/project/core.py
hews/system/projects/project/applications/__init__.py
hews/system/projects/project/applications/core.py
hews/system/projects/project/applications/application/__init__.py
hews/system/projects/project/applications/application/core.py
hews/system/projects/project/applications/application/modules/__init__.py
hews/system/projects/project/applications/application/modules/core.py
hews/system/projects/project/applications/application/modules/module/__init__.py
hews/system/projects/project/applications/application/modules/module/core.py
hews/templates/__init__.py
hews/templates/back_junior_core.py
hews/templates/back_node_core.py
hews/templates/back_senior_core.py
hews/templates/front_module.py
hews-0.0.5.dist-info/LICENSE.rst
hews-0.0.5.dist-info/METADATA
hews-0.0.5.dist-info/WHEEL
hews-0.0.5.dist-info/entry_points.txt
hews-0.0.5.dist-info/top_level.txt
hews-0.0.5.dist-info/RECORD
