Metadata-Version: 2.1
Name: hews
Version: 0.0.5
Summary: Python Websites System
Home-page: https://py.hebill.net/hews
Author: He Bill
Author-email: hebill@me.com
Requires-Python: >=3.12
License-File: LICENSE.rst
Requires-Dist: hehd ==1.0.0
Requires-Dist: heuf ==1.0.0
Requires-Dist: Flask ==3.0.2
Requires-Dist: colorama ==0.4.6
